Handlers/__init__.py
Handlers/log_database_handler.py
core/__init__.py
core/config.py
data/__init__.py
data/external/__init__.py
data/interim/__init__.py
data/processed/__init__.py
data/raw/__init__.py
data/raw/a1_IMDB_Dataset.csv
models/__init__.py
models/sentimentdl_glove_imdb_en.h5
src/__init__.py
src/data/__init__.py
src/data/load_datasets.py
src/data/preprocess_datatsets.py
src/features/__init__.py
src/features/build_features.py
src/models/__init__.py
src/models/predict_model.py
src/models/train_model.py
mhlabs_sentiment-0.0.1.dist-info/LICENSE
mhlabs_sentiment-0.0.1.dist-info/METADATA
mhlabs_sentiment-0.0.1.dist-info/WHEEL
mhlabs_sentiment-0.0.1.dist-info/top_level.txt
mhlabs_sentiment-0.0.1.dist-info/RECORD
