Metadata-Version: 2.1
Name: mhlabs-sentiment
Version: 0.0.1
Summary: In this introductory sample, we'll try to predict a sentiment (positive or negative) for customer reviews. In the world of machine learning, this type of prediction is known as binary classification.
Author-email: MusaddiqueHussain Labs <musaddiquehussainlabs@gmail.com>
Project-URL: Homepage, https://github.com/MusaddiqueHussainLabs/sentimentdl_glove_imdb_en
Project-URL: Bug Tracker, https://github.com/MusaddiqueHussainLabs/sentimentdl_glove_imdb_en/issues
Classifier: Programming Language :: Python :: 3
Classifier: License :: OSI Approved :: MIT License
Classifier: Operating System :: OS Independent
Requires-Python: >=3.7
License-File: LICENSE
Requires-Dist: pandas
Requires-Dist: tensorflow
Requires-Dist: nltk
Requires-Dist: scikit-learn
Requires-Dist: seaborn
Requires-Dist: pyodbc
